smolbpe/__init__.py
smolbpe/tokenizer.py
smolbpe-0.3.2.dist-info/LICENSE
smolbpe-0.3.2.dist-info/METADATA
smolbpe-0.3.2.dist-info/WHEEL
smolbpe-0.3.2.dist-info/entry_points.txt
smolbpe-0.3.2.dist-info/top_level.txt
smolbpe-0.3.2.dist-info/RECORD
